MANIFEST.in
README.rst
setup.py
docs/HISTORY.txt
docs/LICENSE.GPL
docs/LICENSE.txt
ftw/__init__.py
ftw.builder.egg-info/PKG-INFO
ftw.builder.egg-info/SOURCES.txt
ftw.builder.egg-info/dependency_links.txt
ftw.builder.egg-info/namespace_packages.txt
ftw.builder.egg-info/not-zip-safe
ftw.builder.egg-info/requires.txt
ftw.builder.egg-info/top_level.txt
ftw/builder/__init__.py
ftw/builder/archetypes.py
ftw/builder/builder.py
ftw/builder/compat.py
ftw/builder/content.py
ftw/builder/dexterity.py
ftw/builder/genericsetup.py
ftw/builder/group.py
ftw/builder/package.py
ftw/builder/portlets.py
ftw/builder/registry.py
ftw/builder/session.py
ftw/builder/testing.py
ftw/builder/user.py
ftw/builder/utils.py
ftw/builder/zcml.py
ftw/builder/tests/__init__.py
ftw/builder/tests/person.py
ftw/builder/tests/test_archetypes.py
ftw/builder/tests/test_auto_commit.py
ftw/builder/tests/test_builder.py
ftw/builder/tests/test_content.py
ftw/builder/tests/test_dexterity.py
ftw/builder/tests/test_genericsetup_plone_upgrade_builder.py
ftw/builder/tests/test_genericsetup_profile_builder.py
ftw/builder/tests/test_groups.py
ftw/builder/tests/test_package_builder.py
ftw/builder/tests/test_package_zcml_loading.py
ftw/builder/tests/test_person.py
ftw/builder/tests/test_portlets.py
ftw/builder/tests/test_registry.py
ftw/builder/tests/test_users.py
ftw/builder/tests/test_utils.py
ftw/builder/tests/test_zcml_builder.py